docs/Makefile
docs/changelog.rst
docs/conf.py
docs/index.rst
docs/requirements.txt
docs/api/clients.rst
docs/api/decorators.rst
docs/api/index.rst
docs/api/methods.rst
docs/api/types.rst
docs/api/util.rst
docs/contributing/index.rst
yapw/__init__.py
yapw/clients.py
yapw/decorators.py
yapw/methods.py
yapw/ossignal.py
yapw/py.typed
yapw/types.py
yapw/util.py
yapw-0.2.2.dist-info/licenses/LICENSE
yapw-0.2.2.dist-info/METADATA
yapw-0.2.2.dist-info/WHEEL
yapw-0.2.2.dist-info/top_level.txt
yapw-0.2.2.dist-info/RECORD
