Metadata-Version: 2.4
Name: yapw
Version: 0.2.2
Summary: A Pika wrapper with error handling, signal handling and good defaults.
Author-email: Open Contracting Partnership <data@open-contracting.org>
License: BSD
Project-URL: Homepage, https://github.com/open-contracting/yapw
Classifier: License :: OSI Approved :: BSD License
Classifier: Operating System :: POSIX :: Linux
Classifier: Programming Language :: Python :: 3.10
Classifier: Programming Language :: Python :: 3.11
Classifier: Programming Language :: Python :: Implementation :: CPython
Requires-Python: >=3.10
License-File: LICENSE
Requires-Dist: pika>=1.2.0
Provides-Extra: perf
Requires-Dist: orjson; extra == "perf"
Provides-Extra: test
Requires-Dist: coverage; extra == "test"
Requires-Dist: pytest; extra == "test"
Provides-Extra: types
Requires-Dist: mypy; extra == "types"
Requires-Dist: types-orjson; extra == "types"
Requires-Dist: types-pika; extra == "types"
Dynamic: license-file
